arubacentralcaas/.cache/.gitignore
arubacentralcaas/.cache/caascache.json
arubacentralcaas/.gitignore
arubacentralcaas/LICENSE.txt
arubacentralcaas/README.md
arubacentralcaas/__init__.py
arubacentralcaas/app.py
arubacentralcaas/config/.gitignore
arubacentralcaas/config/config.yaml.sample
arubacentralcaas/config/settings.py
arubacentralcaas/deprecated/README.md
arubacentralcaas/deprecated/ac_cookie.py
arubacentralcaas/deprecated/caas.py
arubacentralcaas/deprecated/caastokens.py
arubacentralcaas/deprecated/central_config.py.example
arubacentralcaas/deprecated/cookie_version/README.md
arubacentralcaas/deprecated/cookie_version/ac_cookie.py
arubacentralcaas/deprecated/cookie_version/caascookies.py
arubacentralcaas/deprecated/cookie_version/central_config.py.example
arubacentralcaas/deprecated/lib/__init__.py
arubacentralcaas/deprecated/lib/getapi.py
arubacentralcaas/deprecated/old_README.md
arubacentralcaas/deprecated/show_committed.py
arubacentralcaas/deprecated/token.json.sample
arubacentralcaas/images/caastokens.png
arubacentralcaas/images/show_committed.png
arubacentralcaas/model/__init__.py
arubacentralcaas/model/push_config.py
arubacentralcaas/model/shows.py
arubacentralcaas/model/tests.py
arubacentralcaas/samples/example1.json
arubacentralcaas/samples/example2.json
arubacentralcaas/samples/example3.json
arubacentralcaas/samples/example4.json
arubacentralcaas/test.sh
arubacentralcaas/tests/__init__.py
arubacentralcaas/tests/resources/test_get_gateways.json
arubacentralcaas/tests/resources/test_show_committed.json
arubacentralcaas/tests/resources/test_show_effective.json
arubacentralcaas/tests/runner.py
arubacentralcaas/tests/test_app.py
arubacentralcaas/views/__init__.py
arubacentralcaas/views/displays.py
arubacentralcaas-0.1.5.dist-info/entry_points.txt
arubacentralcaas-0.1.5.dist-info/LICENSE.txt
arubacentralcaas-0.1.5.dist-info/WHEEL
arubacentralcaas-0.1.5.dist-info/METADATA
arubacentralcaas-0.1.5.dist-info/RECORD
