Metadata-Version: 2.1
Name: arubacentralcaas
Version: 0.1.5
Summary: Aruba Central CaaS API CLI
License: MIT
Author: Michael Rose Jr.
Author-email: michael@michaelrosejr.com
Requires-Python: >=3.9,<4.0
Classifier: License :: OSI Approved :: MIT License
Classifier: Programming Language :: Python :: 3
Classifier: Programming Language :: Python :: 3.10
Classifier: Programming Language :: Python :: 3.9
Requires-Dist: ipaddress (>=1.0.23,<2.0.0)
Requires-Dist: loguru (>=0.6.0,<0.7.0)
Requires-Dist: pycentral (>=0.0.3,<0.0.4)
Requires-Dist: pydantic (>=1.9.0,<2.0.0)
Requires-Dist: rich (>=12.3.0,<13.0.0)
Requires-Dist: typer (>=0.4.1,<0.5.0)
